{"type":"FeatureCollection", "features": [
{"type":"Feature","geometry":{"type":"Polygon","coordinates":[[[-116.49999999999994,32.75000000000006],[-116.49999999999994,32.87500000000006],[-116.62499999999994,32.87500000000006],[-116.62499999999994,32.75000000000006],[-116.49999999999994,32.75000000000006]]]},"properties":{"OBJECTID":1,"CELL_ID":12030,"CELL_NAME":"Descanso","PRIMARY_ST":"California","STATE_ALPH":"CA","SEQ_GOVTUN":"06073","CELL_MAPCO":"32116-G5","CELL_TYPE":1,"CELL_ALLWA":2,"CELL_DESCR":"","CELL_DIACR":"","ISNOPRIM":0,"ISMULTPRIM":0,"ISPRIMDIFF":0,"GLOBALID":"{907CA3B0-CDC4-4A50-8EFE-C4C888A9FB90}","SHAPE_Leng":0.5,"SHAPE_Area":0.015625}},
{"type":"Feature","geometry":{"type":"Polygon","coordinates":[[[-116.49999999999994,32.50000000000006],[-116.37499999999994,32.50000000000006],[-116.37499999999994,32.62500000000006],[-116.49999999999994,32.62500000000006],[-116.49999999999994,32.50000000000006]]]},"properties":{"OBJECTID":2,"CELL_ID":6974,"CELL_NAME":"Campo","PRIMARY_ST":"California","STATE_ALPH":"CA,BCN","SEQ_GOVTUN":"06073,MX02","CELL_MAPCO":"32116-E4","CELL_TYPE":1,"CELL_ALLWA":2,"CELL_DESCR":"","CELL_DIACR":"","ISNOPRIM":0,"ISMULTPRIM":0,"ISPRIMDIFF":0,"GLOBALID":"{1809AB2B-638F-4FA8-A074-F0CA92FF04EC}","SHAPE_Leng":0.5,"SHAPE_Area":0.015625}},
{"type":"Feature","geometry":{"type":"Polygon","coordinates":[[[-116.62499999999994,32.62500000000006],[-116.62499999999994,32.75000000000006],[-116.74999999999994,32.75000000000006],[-116.74999999999994,32.62500000000006],[-116.62499999999994,32.62500000000006]]]},"properties":{"OBJECTID":3,"CELL_ID":2481,"CELL_NAME":"Barrett Lake","PRIMARY_ST":"California","STATE_ALPH":"CA","SEQ_GOVTUN":"06073","CELL_MAPCO":"32116-F6","CELL_TYPE":1,"CELL_ALLWA":2,"CELL_DESCR":"","CELL_DIACR":"","ISNOPRIM":0,"ISMULTPRIM":0,"ISPRIMDIFF":0,"GLOBALID":"{AC104D20-87F4-430A-B9F5-20350ACFF2AB}","SHAPE_Leng":0.5,"SHAPE_Area":0.015625}},
{"type":"Feature","geometry":{"type":"Polygon","coordinates":[[[-116.62499999999994,32.50000000000006],[-116.62499999999994,32.62500000000006],[-116.74999999999994,32.62500000000006],[-116.74999999999994,32.50000000000006],[-116.62499999999994,32.50000000000006]]]},"properties":{"OBJECTID":4,"CELL_ID":44435,"CELL_NAME":"Tecate","PRIMARY_ST":"California","STATE_ALPH":"CA,BCN","SEQ_GOVTUN":"06073,MX02","CELL_MAPCO":"32116-E6","CELL_TYPE":1,"CELL_ALLWA":2,"CELL_DESCR":"","CELL_DIACR":"","ISNOPRIM":0,"ISMULTPRIM":0,"ISPRIMDIFF":0,"GLOBALID":"{481BB28D-1FB7-4447-AF71-6A1B19EC9483}","SHAPE_Leng":0.5,"SHAPE_Area":0.015625}},
{"type":"Feature","geometry":{"type":"Polygon","coordinates":[[[-116.49999999999994,32.50000000000006],[-116.49999999999994,32.62500000000006],[-116.62499999999994,32.62500000000006],[-116.62499999999994,32.50000000000006],[-116.49999999999994,32.50000000000006]]]},"properties":{"OBJECTID":5,"CELL_ID":36188,"CELL_NAME":"Potrero","PRIMARY_ST":"California","STATE_ALPH":"CA,BCN","SEQ_GOVTUN":"06073,MX02","CELL_MAPCO":"32116-E5","CELL_TYPE":1,"CELL_ALLWA":2,"CELL_DESCR":"","CELL_DIACR":"","ISNOPRIM":0,"ISMULTPRIM":0,"ISPRIMDIFF":0,"GLOBALID":"{4D19083B-6CAB-47EC-834F-B7B8A6F66C43}","SHAPE_Leng":0.5,"SHAPE_Area":0.015625}},
{"type":"Feature","geometry":{"type":"Polygon","coordinates":[[[-116.37499999999994,32.75000000000006],[-116.37499999999994,32.87500000000006],[-116.49999999999994,32.87500000000006],[-116.49999999999994,32.75000000000006],[-116.37499999999994,32.75000000000006]]]},"properties":{"OBJECTID":6,"CELL_ID":30682,"CELL_NAME":"Mount Laguna","PRIMARY_ST":"California","STATE_ALPH":"CA","SEQ_GOVTUN":"06073","CELL_MAPCO":"32116-G4","CELL_TYPE":1,"CELL_ALLWA":2,"CELL_DESCR":"","CELL_DIACR":"","ISNOPRIM":0,"ISMULTPRIM":0,"ISPRIMDIFF":0,"GLOBALID":"{F9EBF4D0-4326-420E-B7C4-2A23CC8D1DEE}","SHAPE_Leng":0.5,"SHAPE_Area":0.015625}},
{"type":"Feature","geometry":{"type":"Polygon","coordinates":[[[-116.62499999999994,32.75000000000006],[-116.62499999999994,32.87500000000006],[-116.74999999999994,32.87500000000006],[-116.74999999999994,32.75000000000006],[-116.62499999999994,32.75000000000006]]]},"properties":{"OBJECTID":7,"CELL_ID":46904,"CELL_NAME":"Viejas Mountain","PRIMARY_ST":"California","STATE_ALPH":"CA","SEQ_GOVTUN":"06073","CELL_MAPCO":"32116-G6","CELL_TYPE":1,"CELL_ALLWA":2,"CELL_DESCR":"","CELL_DIACR":"","ISNOPRIM":0,"ISMULTPRIM":0,"ISPRIMDIFF":0,"GLOBALID":"{1BFCE1CF-4529-410B-AC3F-405241388111}","SHAPE_Leng":0.5,"SHAPE_Area":0.015625}},
{"type":"Feature","geometry":{"type":"Polygon","coordinates":[[[-116.49999999999994,32.62500000000006],[-116.49999999999994,32.75000000000006],[-116.62499999999994,32.75000000000006],[-116.62499999999994,32.62500000000006],[-116.49999999999994,32.62500000000006]]]},"properties":{"OBJECTID":8,"CELL_ID":30197,"CELL_NAME":"Morena Reservoir","PRIMARY_ST":"California","STATE_ALPH":"CA","SEQ_GOVTUN":"06073","CELL_MAPCO":"32116-F5","CELL_TYPE":1,"CELL_ALLWA":2,"CELL_DESCR":"","CELL_DIACR":"","ISNOPRIM":0,"ISMULTPRIM":0,"ISPRIMDIFF":0,"GLOBALID":"{51EB001B-82A4-4A55-A5EE-53D9EB07A274}","SHAPE_Leng":0.5,"SHAPE_Area":0.015625}},
{"type":"Feature","geometry":{"type":"Polygon","coordinates":[[[-116.37499999999994,32.62500000000006],[-116.37499999999994,32.75000000000006],[-116.49999999999994,32.75000000000006],[-116.49999999999994,32.62500000000006],[-116.37499999999994,32.62500000000006]]]},"properties":{"OBJECTID":9,"CELL_ID":6886,"CELL_NAME":"Cameron Corners","PRIMARY_ST":"California","STATE_ALPH":"CA","SEQ_GOVTUN":"06073","CELL_MAPCO":"32116-F4","CELL_TYPE":1,"CELL_ALLWA":2,"CELL_DESCR":"","CELL_DIACR":"","ISNOPRIM":0,"ISMULTPRIM":0,"ISPRIMDIFF":0,"GLOBALID":"{43D9A540-897D-4515-80F0-CBB25B9E80B7}","SHAPE_Leng":0.5,"SHAPE_Area":0.015625}}
]}